[{"type":"sprite","x":0,"y":0,"name":"frame0","0":{"x":169.95,"y":97.5,"w":933.65,"h":43.8,"name":"tip","type":"text","r":0,"txt":"用放大镜观察晶体","a":"center","f":"35px '方正大黑简体'","c":"#FFFFFF"},"1":{"x":0,"y":0,"name":"step0","type":"sprite","r":0,"sx":1,"sy":1,"a":1,"skewX":0,"skewY":0,"0":{"x":1000,"y":350,"name":"glass","type":"sprite","r":0,"sx":1,"sy":1,"a":1,"skewX":0,"skewY":0,"0":{"type":"bitmap","libName":"Bitmap 7","x":-103.5,"y":-101.45,"r":0,"sx":1,"sy":1,"skewX":0,"skewY":0},"1":{"x":126.2,"y":-102,"name":"tipIcon","type":"sprite","r":0,"sx":1,"sy":1,"a":1,"skewX":0,"skewY":0,"0":{"type":"bitmap","libName":"Bitmap 4","x":-14,"y":-16,"r":0,"sx":1,"sy":1,"skewX":0,"skewY":0}},"2":{"x":112.2,"y":-78.95,"name":"littleTip","type":"sprite","r":0,"sx":1,"sy":1,"a":1,"skewX":0,"skewY":0,"0":{"type":"bitmap","libName":"Bitmap 3","x":0,"y":0,"r":0,"sx":1,"sy":1,"skewX":0,"skewY":0}}},"1":{"x":-191.95,"y":349.8,"name":"bigPng0","type":"sprite","r":0,"sx":1,"sy":1,"a":1,"skewX":0,"skewY":0,"0":{"type":"bitmap","libName":"y.png","x":-400,"y":-225,"r":0,"sx":1,"sy":1,"skewX":0,"skewY":0}},"2":{"x":100,"y":100,"name":"bottom","type":"sprite","r":0,"sx":1,"sy":1,"a":1,"skewX":0,"skewY":0,"0":{"type":"bitmap","libName":"Bitmap 2","x":-100,"y":-100,"r":0,"sx":1,"sy":1,"skewX":0,"skewY":0}},"3":{"x":637.7,"y":357.4,"name":"sPng0","type":"sprite","r":0,"sx":1,"sy":1,"a":1,"skewX":0,"skewY":0,"0":{"type":"bitmap","libName":"盐.png","x":-200,"y":-111.5,"r":0,"sx":1,"sy":1,"skewX":0,"skewY":0}},"4":{"x":633.75,"y":345.9,"name":"glassMask","type":"sprite","r":0,"sx":0.9829254150390625,"sy":0.8263702392578125,"a":1,"skewX":0,"skewY":0,"0":{"type":"shape","path":[255,-218.65,468.7,2,247.95,468.7,2,247.95,-468.7,2,-218.65,-468.7,-230.75,-468.7,-239.35,-459.95,3,-239.35,-459.95,-242.5,-456.75,-244.45,-453.15,3,-244.45,-453.15,-247.9,-446.75,-247.9,-439,3,-247.9,-439,2,-247.9,439,-247.9,451.3,-239.35,460,3,-239.35,460,-230.75,468.7,-218.65,468.7,3,1,3819871,33]}}},"2":{"x":0,"y":0,"name":"step1","type":"sprite","r":0,"sx":1,"sy":1,"a":1,"skewX":0,"skewY":0,"0":{"x":1000,"y":350,"name":"glass","type":"sprite","r":0,"sx":1,"sy":1,"a":1,"skewX":0,"skewY":0,"0":{"type":"bitmap","libName":"Bitmap 7","x":-103.5,"y":-101.45,"r":0,"sx":1,"sy":1,"skewX":0,"skewY":0},"1":{"x":126.2,"y":-102,"name":"tipIcon","type":"sprite","r":0,"sx":1,"sy":1,"a":1,"skewX":0,"skewY":0,"0":{"type":"bitmap","libName":"Bitmap 4","x":-14,"y":-16,"r":0,"sx":1,"sy":1,"skewX":0,"skewY":0}},"2":{"x":112.2,"y":-78.95,"name":"littleTip","type":"sprite","r":0,"sx":1,"sy":1,"a":1,"skewX":0,"skewY":0,"0":{"type":"bitmap","libName":"Bitmap 3","x":0,"y":0,"r":0,"sx":1,"sy":1,"skewX":0,"skewY":0}}},"1":{"x":-185.85,"y":334.85,"name":"bigPng0","type":"sprite","r":0,"sx":1,"sy":1,"a":1,"skewX":0,"skewY":0,"0":{"type":"bitmap","libName":"t.png","x":-400,"y":-225,"r":0,"sx":1,"sy":1,"skewX":0,"skewY":0}},"2":{"x":100,"y":100,"name":"bottom","type":"sprite","r":0,"sx":1,"sy":1,"a":1,"skewX":0,"skewY":0,"0":{"type":"bitmap","libName":"Bitmap 2","x":-100,"y":-100,"r":0,"sx":1,"sy":1,"skewX":0,"skewY":0}},"3":{"x":637.65,"y":368.2,"name":"sPng0","type":"sprite","r":0,"sx":1,"sy":1,"a":1,"skewX":0,"skewY":0,"0":{"type":"bitmap","libName":"糖.png","x":-200,"y":-112.5,"r":0,"sx":1,"sy":1,"skewX":0,"skewY":0}},"4":{"x":633.5,"y":343.4,"name":"glassMask","type":"sprite","r":0,"sx":0.9829254150390625,"sy":0.8263702392578125,"a":1,"skewX":0,"skewY":0,"0":{"type":"shape","path":[255,-218.65,468.7,2,247.95,468.7,2,247.95,-468.7,2,-218.65,-468.7,-230.75,-468.7,-239.35,-459.95,3,-239.35,-459.95,-242.5,-456.75,-244.45,-453.15,3,-244.45,-453.15,-247.9,-446.75,-247.9,-439,3,-247.9,-439,2,-247.9,439,-247.9,451.3,-239.35,460,3,-239.35,460,-230.75,468.7,-218.65,468.7,3,1,3819871,33]}}},"3":{"x":0,"y":0,"name":"step2","type":"sprite","r":0,"sx":1,"sy":1,"a":1,"skewX":0,"skewY":0,"0":{"x":1000,"y":350,"name":"glass","type":"sprite","r":0,"sx":1,"sy":1,"a":1,"skewX":0,"skewY":0,"0":{"type":"bitmap","libName":"Bitmap 7","x":-103.5,"y":-101.45,"r":0,"sx":1,"sy":1,"skewX":0,"skewY":0},"1":{"x":126.2,"y":-102,"name":"tipIcon","type":"sprite","r":0,"sx":1,"sy":1,"a":1,"skewX":0,"skewY":0,"0":{"type":"bitmap","libName":"Bitmap 4","x":-14,"y":-16,"r":0,"sx":1,"sy":1,"skewX":0,"skewY":0}},"2":{"x":112.2,"y":-78.95,"name":"littleTip","type":"sprite","r":0,"sx":1,"sy":1,"a":1,"skewX":0,"skewY":0,"0":{"type":"bitmap","libName":"Bitmap 3","x":0,"y":0,"r":0,"sx":1,"sy":1,"skewX":0,"skewY":0}}},"1":{"x":-204,"y":341.5,"name":"bigPng0","type":"sprite","r":0,"sx":1,"sy":1,"a":1,"skewX":0,"skewY":0,"0":{"type":"bitmap","libName":"w.png","x":-400,"y":-225,"r":0,"sx":1,"sy":1,"skewX":0,"skewY":0}},"2":{"x":100,"y":100,"name":"bottom","type":"sprite","r":0,"sx":1,"sy":1,"a":1,"skewX":0,"skewY":0,"0":{"type":"bitmap","libName":"Bitmap 2","x":-100,"y":-100,"r":0,"sx":1,"sy":1,"skewX":0,"skewY":0}},"3":{"x":639.65,"y":368.2,"name":"sPng0","type":"sprite","r":0,"sx":1,"sy":1,"a":1,"skewX":0,"skewY":0,"0":{"type":"bitmap","libName":"味精.png","x":-200.1,"y":-112.5,"r":0,"sx":1,"sy":1,"skewX":0,"skewY":0}},"4":{"x":633.75,"y":345.85,"name":"glassMask","type":"sprite","r":0,"sx":0.9829254150390625,"sy":0.8263702392578125,"a":1,"skewX":0,"skewY":0,"0":{"type":"shape","path":[255,-218.65,468.7,2,247.95,468.7,2,247.95,-468.7,2,-218.65,-468.7,-230.75,-468.7,-239.35,-459.95,3,-239.35,-459.95,-242.5,-456.75,-244.45,-453.15,3,-244.45,-453.15,-247.9,-446.75,-247.9,-439,3,-247.9,-439,2,-247.9,439,-247.9,451.3,-239.35,460,3,-239.35,460,-230.75,468.7,-218.65,468.7,3,1,3819871,33]}}},"4":{"x":315.85,"y":590.55,"name":"timeline","type":"sprite","r":0,"sx":1,"sy":1,"a":1,"skewX":0,"skewY":0,"0":{"x":419.05,"y":32.55,"w":104,"h":32.4,"name":"","type":"text","r":0,"txt":"味精","a":"center","f":"25px '方正大黑简体'","c":"#FFFFFF"},"1":{"x":269.3,"y":32.55,"w":104,"h":32.4,"name":"","type":"text","r":0,"txt":"糖","a":"center","f":"25px '方正大黑简体'","c":"#FFFFFF"},"2":{"x":118.75,"y":32.55,"w":104,"h":32.4,"name":"","type":"text","r":0,"txt":"食盐","a":"center","f":"25px '方正大黑简体'","c":"#FFFFFF"},"3":{"x":133.25,"y":-30.05,"name":"drag","type":"sprite","r":0,"sx":1,"sy":1,"a":1,"skewX":0,"skewY":0,"0":{"type":"bitmap","libName":"timeline_bhitArea1","x":-0.3,"y":-0.3,"r":0,"sx":1.471923828125,"sy":1.471923828125,"skewX":0,"skewY":0},"1":{"type":"bitmap","libName":"timeline_bcircle_11","x":26.5,"y":26.5,"r":0,"sx":0.399993896484375,"sy":0.399993896484375,"skewX":0,"skewY":0}},"4":{"x":433.25,"y":-30.05,"name":"a2","type":"sprite","r":0,"sx":1,"sy":1,"a":1,"skewX":0,"skewY":0,"0":{"type":"bitmap","libName":"timeline_bhitArea1","x":-0.3,"y":-0.3,"r":0,"sx":1.471923828125,"sy":1.471923828125,"skewX":0,"skewY":0},"1":{"type":"bitmap","libName":"timeline_bcircle_21","x":26.5,"y":26.5,"r":0,"sx":0.399993896484375,"sy":0.399993896484375,"skewX":0,"skewY":0}},"5":{"x":283.25,"y":-30.05,"name":"a1","type":"sprite","r":0,"sx":1,"sy":1,"a":1,"skewX":0,"skewY":0,"0":{"type":"bitmap","libName":"timeline_bhitArea1","x":-0.3,"y":-0.3,"r":0,"sx":1.471923828125,"sy":1.471923828125,"skewX":0,"skewY":0},"1":{"type":"bitmap","libName":"timeline_bcircle_21","x":26.5,"y":26.5,"r":0,"sx":0.399993896484375,"sy":0.399993896484375,"skewX":0,"skewY":0}},"6":{"x":133.25,"y":-30.05,"name":"a0","type":"sprite","r":0,"sx":1,"sy":1,"a":1,"skewX":0,"skewY":0,"0":{"type":"bitmap","libName":"timeline_bhitArea1","x":-0.3,"y":-0.3,"r":0,"sx":1.471923828125,"sy":1.471923828125,"skewX":0,"skewY":0},"1":{"type":"bitmap","libName":"timeline_bcircle_21","x":26.5,"y":26.5,"r":0,"sx":0.399993896484375,"sy":0.399993896484375,"skewX":0,"skewY":0}}},"5":{"type":"bitmap","libName":"Bitmap 1","x":-15.25,"y":22.4,"r":0,"sx":1.013916015625,"sy":1.0139617919921875,"skewX":0,"skewY":0}},{"name":"ei","x":0,"y":0,"type":"sprite"},{"name":"ee","x":0,"y":0,"type":"sprite"},{"name":"cc","x":0,"y":0,"type":"sprite"}]